datsluo_sj_mcp/__init__.py
datsluo_sj_mcp/main.py
datsluo_sj_mcp/tools/__init__.py
datsluo_sj_mcp/tools/patent_search.py
datsluo_sj_mcp/tools.py
datsluo_sj_mcp-0.1.0.dist-info/WHEEL
datsluo_sj_mcp-0.1.0.dist-info/entry_points.txt
datsluo_sj_mcp-0.1.0.dist-info/METADATA
datsluo_sj_mcp-0.1.0.dist-info/RECORD
