Metadata-Version: 2.3
Name: datsluo_sj_mcp
Version: 0.1.0
Summary: Add your description here
Author: dats
Author-email: dats <2292303916@qq.com>
Requires-Dist: dashscope==1.24.4
Requires-Dist: fastmcp>=2.14.1
Requires-Dist: pydantic>=2.12.5
Requires-Dist: python-dotenv>=1.0.0
Requires-Dist: requests>=2.31.0
Requires-Python: >=3.10
